admin_honeypot/__init__.py
admin_honeypot/admin.py
admin_honeypot/apps.py
admin_honeypot/forms.py
admin_honeypot/listeners.py
admin_honeypot/models.py
admin_honeypot/signals.py
admin_honeypot/urls.py
admin_honeypot/views.py
admin_honeypot/locale/es_ES/LC_MESSAGES/django.mo
admin_honeypot/locale/es_ES/LC_MESSAGES/django.po
admin_honeypot/locale/ru/LC_MESSAGES/django.mo
admin_honeypot/locale/ru/LC_MESSAGES/django.po
admin_honeypot/locale/zh_CN/LC_MESSAGES/django.mo
admin_honeypot/locale/zh_CN/LC_MESSAGES/django.po
admin_honeypot/locale/zh_Hans/LC_MESSAGES/django.mo
admin_honeypot/locale/zh_Hans/LC_MESSAGES/django.po
admin_honeypot/migrations/0001_initial.py
admin_honeypot/migrations/0002_auto_20160208_0854.py
admin_honeypot/migrations/__init__.py
admin_honeypot/templates/admin_honeypot/email_message.txt
admin_honeypot/templates/admin_honeypot/email_subject.txt
admin_honeypot/templates/admin_honeypot/login.html
tests/__init__.py
tests/settings.py
tests/test_suite.py
tests/urls.py
django_admin_honeypot_dlan-1.1.0.dist-info/LICENSE
django_admin_honeypot_dlan-1.1.0.dist-info/METADATA
django_admin_honeypot_dlan-1.1.0.dist-info/WHEEL
django_admin_honeypot_dlan-1.1.0.dist-info/top_level.txt
django_admin_honeypot_dlan-1.1.0.dist-info/RECORD
