Metadata-Version: 2.1
Name: django-admin-honeypot-dlan
Version: 1.1.0
Summary: A fake Django admin login screen to notify admins of attempted unauthorized access.
Home-page: https://github.com/DeeeeLAN/django-admin-honeypot-dlan
Download-URL: https://github.com/DeeeeLAN/django-admin-honeypot-dlan/tarball/v1.1.0
Maintainer: Derek Payton
Maintainer-email: derek.payton@gmail.com
License: MIT License
Keywords: django admin honeypot trap
Platform: UNKNOWN
Classifier: Development Status :: 5 - Production/Stable
Classifier: Framework :: Django
Classifier: Framework :: Django :: 2.2
Classifier: Framework :: Django :: 3.0
Classifier: Intended Audience :: Developers
Classifier: License :: OSI Approved :: MIT License
Classifier: Natural Language :: English
Classifier: Operating System :: OS Independent
Classifier: Programming Language :: Python
Classifier: Programming Language :: Python :: 3
Classifier: Programming Language :: Python :: 3.5
Classifier: Programming Language :: Python :: 3.6
Classifier: Programming Language :: Python :: 3.7
Classifier: Programming Language :: Python :: 3.8
Classifier: Topic :: Internet :: WWW/HTTP :: Dynamic Content
License-File: LICENSE
Requires-Dist: django-ipware
